{"id":"special-permissions-sticky-bit","name":"special permissions (sticky bit)","description":"","author":"1","last_modified":"2015-04-11 18:58:05","data":[["Permission","Files","Directories"],["Set User ID  (SUID)","Run executable files as owner","n\/a"],["Set Group ID (SGID)","Run Executable files as group owner","Inherits Group ownership to all newly created items"],["Sticky bit","n\/a","Delete files only if owner or owner of the parent directory"]],"options":{"last_editor":1,"table_head":true,"table_foot":false,"alternating_row_colors":true,"row_hover":true,"print_name":false,"print_name_position":"above","print_description":false,"print_description_position":"below","extra_css_classes":"","use_datatables":false,"datatables_sort":true,"datatables_filter":true,"datatables_paginate":true,"datatables_lengthchange":true,"datatables_paginate_entries":10,"datatables_info":true,"datatables_scrollx":false,"datatables_custom_commands":""},"visibility":{"rows":[1,1,1,1],"columns":[1,1,1]}}